MANIFEST.in
README.rst
pyproject.toml
requirements.txt
setup.cfg
setup.py
iqdb_tagger/__init__.py
iqdb_tagger/__main__.py
iqdb_tagger/custom_parser.py
iqdb_tagger/forms.py
iqdb_tagger/models.py
iqdb_tagger/parse.py
iqdb_tagger/sha256.py
iqdb_tagger/utils.py
iqdb_tagger/views.py
iqdb_tagger.egg-info/PKG-INFO
iqdb_tagger.egg-info/SOURCES.txt
iqdb_tagger.egg-info/dependency_links.txt
iqdb_tagger.egg-info/entry_points.txt
iqdb_tagger.egg-info/requires.txt
iqdb_tagger.egg-info/top_level.txt
iqdb_tagger/templates/layout.html
iqdb_tagger/templates/iqdb_tagger/index.html
iqdb_tagger/templates/iqdb_tagger/match.html
iqdb_tagger/templates/iqdb_tagger/match_checksum.html
iqdb_tagger/templates/iqdb_tagger/match_single.html