Metadata-Version: 2.1
Name: iqdb-tagger
Version: 0.3.2
Summary: Get result from iqdb.org.
Home-page: https://github.com/softashell/iqdb_tagger
Author: softashell
Maintainer: Rachmadani Haryono
Maintainer-email: foreturiga@gmail.com
License: MIT
Download-URL: https://github.com/softashell/iqdb_tagger/tarball/0.3.2
Platform: UNKNOWN
Classifier: License :: OSI Approved :: MIT License
Classifier: Development Status :: 3 - Alpha
Classifier: Intended Audience :: Developers
Classifier: Programming Language :: Python :: 3
Provides-Extra: doc
Provides-Extra: dev
